avania/__init__.py
avania/orm/__init__.py
avania/orm/driver/__init__.py
avania/orm/driver/mysql/__init__.py
avania/orm/driver/mysql/database.py
avania/orm/driver/mysql/mate.py
avania/orm/driver/mysql/mysqli.py
avania/sys/__init__.py
avania/sys/config/__init__.py
avania/sys/config/config.py
avania/sys/config/meta.py
avania/sys/config/templates/__init__.py
avania/sys/config/templates/database.py
avania/sys/os/__init__.py
avania/sys/os/config.py
avania/sys/os/os.py
avania/sys/prompt/__init__.py
avania/sys/prompt/prompt.py
avania-0.1.8.dist-info/LICENSE
avania-0.1.8.dist-info/METADATA
avania-0.1.8.dist-info/WHEEL
avania-0.1.8.dist-info/top_level.txt
avania-0.1.8.dist-info/RECORD
