Metadata-Version: 2.1
Name: avania
Version: 0.1.8
Summary: Pays tribute to Laravel
Author: Simon
License-File: LICENSE
Requires-Dist: mysql-connector-python
Requires-Dist: flask
